itculate_sdk/__init__.py
itculate_sdk/connection.py
itculate_sdk/dictionary.py
itculate_sdk/exceptions.py
itculate_sdk/graph.py
itculate_sdk/local_credentials.py
itculate_sdk/payload.py
itculate_sdk/provider.py
itculate_sdk/sample.py
itculate_sdk/types.py
itculate_sdk/utils.py
itculate_sdk/examples/__init__.py
itculate_sdk/examples/architecture.py
itculate_sdk/examples/cost_analysis.py
itculate_sdk/examples/file_processor.py
itculate_sdk/examples/k8s.py
itculate_sdk/examples/logic_monitor_rest_client.py
itculate_sdk/examples/logicmonitor.py
itculate_sdk/examples/logicmonitor_services.py
itculate_sdk/examples/logicmonitor_vmware.py
itculate_sdk/examples/playground.py
itculate_sdk/examples/step_function.py
itculate_sdk/examples/util.py
itculate_sdk/examples/vpc_flow_logs.py
itculate_sdk/statsd/__init__.py
itculate_sdk/statsd/statsd.py
itculate_sdk-0.14.14.dist-info/METADATA
itculate_sdk-0.14.14.dist-info/RECORD
itculate_sdk-0.14.14.dist-info/WHEEL
itculate_sdk-0.14.14.dist-info/top_level.txt
