Metadata-Version: 2.1
Name: itculate-sdk
Version: 0.14.14
Summary: ITculate SDK
Home-page: https://bitbucket.org/itculate/itculate-sdk
Author: Ran
Author-email: opensource@itculate.io
License: MIT
Keywords: ITculate,sdk,graph,topology
Platform: UNKNOWN
Requires-Dist: six (>=1.10.0)
Requires-Dist: requests (>=2.12.4)
Requires-Dist: unix-dates (>=0.4.1)
Requires-Dist: msgpack-python (>=0.4.8)
